highfrequency/__init__.py
highfrequency/data_handling.py
highfrequency/internal_data_handling.py
highfrequency/helpers/__init__.py
highfrequency/helpers/exchange_names.py
highfrequency/helpers/schemas.py
tests/__init__.py
tests/test_data_handling.py
tests/test_internal_data_handling.py
highfrequency-0.1.0.dist-info/LICENSE
highfrequency-0.1.0.dist-info/METADATA
highfrequency-0.1.0.dist-info/WHEEL
highfrequency-0.1.0.dist-info/top_level.txt
highfrequency-0.1.0.dist-info/RECORD
