Metadata-Version: 2.1
Name: highfrequency
Version: 0.1.0
Summary: Implementation of the HighFrequency R package in Python.
Author: Patrick Lucescu
Author-email: patricklucescu@outlook.com
License: MIT
Classifier: Programming Language :: Python :: 3.12
Classifier: License :: OSI Approved :: MIT License
Classifier: Operating System :: OS Independent
Classifier: Development Status :: 1 - Planning
Requires-Python: >=3.12
License-File: LICENSE
Requires-Dist: polars
Requires-Dist: pytest
Requires-Dist: pandas
Requires-Dist: numpy
